<annotation>
	<folder>test</folder>
	<filename>out15.jpg</filename>
	<path>C:\Users\danie\Repos\Uni\Honours\Object-Detection_Python_Honours_4th_Year\workspace\training_setup\images\test\out15.jpg</path>
	<source>
		<database>Unknown</database>
	</source>
	<size>
		<width>960</width>
		<height>540</height>
		<depth>3</depth>
	</size>
	<segmented>0</segmented>
	<object>
		<name>Duck</name>
		<pose>Unspecified</pose>
		<truncated>0</truncated>
		<difficult>0</difficult>
		<bndbox>
			<xmin>611</xmin>
			<ymin>180</ymin>
			<xmax>735</xmax>
			<ymax>334</ymax>
		</bndbox>
	</object>
</annotation>
